botnoi_dev_platform/__init__.py
botnoi_dev_platform-0.0.8.dist-info/METADATA
botnoi_dev_platform-0.0.8.dist-info/WHEEL
botnoi_dev_platform-0.0.8.dist-info/top_level.txt
botnoi_dev_platform-0.0.8.dist-info/RECORD
