Metadata-Version: 2.1
Name: botnoi-dev-platform
Version: 0.0.8
Summary: A programatical alternative to the visual chatbot builder provided by https://botnoi.ai . 
Author: Jira Pit @ BOTNOI GROUP
Author-email: <jira.p@botnoigroup.com>
Maintainer: Jira Pit @ BOTNOI GROUP
Maintainer-email: <jira.p@botnoigroup.com>
Keywords: botnoi,chatbot,bot,botnoi dev platform
Classifier: Programming Language :: Python :: 3.9
Classifier: Operating System :: Unix
Classifier: Operating System :: MacOS :: MacOS X
Classifier: Operating System :: Microsoft :: Windows
Requires-Dist: requests
